rationalize_sqrt/rationalize_sqrt.py
rationalize_sqrt-0.7.1.dist-info/METADATA
rationalize_sqrt-0.7.1.dist-info/WHEEL
rationalize_sqrt-0.7.1.dist-info/licenses/LICENSE.md
rationalize_sqrt-0.7.1.dist-info/RECORD
