Metadata-Version: 2.4
Name: rationalize_sqrt
Version: 0.7.1
Summary: command-line app for finding multipliers of square roots
License-File: LICENSE.md
Author: K1CE
Author-email: 6kouman@gmail.com
Requires-Python: >=3.9
Classifier: Programming Language :: Python :: 3
Classifier: Programming Language :: Python :: 3.9
Classifier: Programming Language :: Python :: 3.10
Classifier: Programming Language :: Python :: 3.11
Classifier: Programming Language :: Python :: 3.12
Classifier: Programming Language :: Python :: 3.13
Classifier: Programming Language :: Python :: 3.14
Project-URL: GitHub, https://github.com/K1CE/Square-Root_rationalizer
